{
    "3001": "Herisau",
    "3002": "Hundwil",
    "3003": "Sch\u00f6nengrund",
    "3004": "Schwellbrunn",
    "3005": "Stein (AR)",
    "3006": "Urn\u00e4sch",
    "3007": "Waldstatt",
    "3021": "B\u00fchler",
    "3022": "Gais",
    "3023": "Speicher",
    "3024": "Teufen (AR)",
    "3025": "Trogen",
    "3031": "Grub (AR)",
    "3032": "Heiden",
    "3033": "Lutzenberg",
    "3034": "Rehetobel",
    "3035": "Reute (AR)",
    "3036": "Wald (AR)",
    "3037": "Walzenhausen",
    "3038": "Wolfhalden"
}